dglgo/__init__.py
dglgo/apply_pipeline/__init__.py
dglgo/apply_pipeline/graphpred/__init__.py
dglgo/apply_pipeline/graphpred/gen.py
dglgo/apply_pipeline/graphpred/graphpred.jinja-py
dglgo/apply_pipeline/nodepred/__init__.py
dglgo/apply_pipeline/nodepred/gen.py
dglgo/apply_pipeline/nodepred/nodepred.jinja-py
dglgo/apply_pipeline/nodepred_sample/__init__.py
dglgo/apply_pipeline/nodepred_sample/gen.py
dglgo/apply_pipeline/nodepred_sample/nodepred-ns.jinja-py
dglgo/cli/__init__.py
dglgo/cli/apply_cli.py
dglgo/cli/cli.py
dglgo/cli/config_apply_cli.py
dglgo/cli/config_cli.py
dglgo/cli/export_cli.py
dglgo/cli/recipe_cli.py
dglgo/cli/train_cli.py
dglgo/model/__init__.py
dglgo/model/edge_encoder/__init__.py
dglgo/model/edge_encoder/bilinear.py
dglgo/model/edge_encoder/dot.py
dglgo/model/edge_encoder/ele.py
dglgo/model/graph_encoder/__init__.py
dglgo/model/graph_encoder/gin_ogbg.py
dglgo/model/graph_encoder/pna.py
dglgo/model/node_encoder/__init__.py
dglgo/model/node_encoder/gat.py
dglgo/model/node_encoder/gcn.py
dglgo/model/node_encoder/gin.py
dglgo/model/node_encoder/sage.py
dglgo/model/node_encoder/sgc.py
dglgo/pipeline/__init__.py
dglgo/pipeline/graphpred/__init__.py
dglgo/pipeline/graphpred/gen.py
dglgo/pipeline/graphpred/graphpred.jinja-py
dglgo/pipeline/linkpred/__init__.py
dglgo/pipeline/linkpred/gen.py
dglgo/pipeline/linkpred/linkpred.jinja-py
dglgo/pipeline/nodepred/__init__.py
dglgo/pipeline/nodepred/gen.py
dglgo/pipeline/nodepred/nodepred.jinja-py
dglgo/pipeline/nodepred_sample/__init__.py
dglgo/pipeline/nodepred_sample/gen.py
dglgo/pipeline/nodepred_sample/nodepred-ns.jinja-py
dglgo/utils/__init__.py
dglgo/utils/base_model.py
dglgo/utils/early_stop.py
dglgo/utils/enter_config.py
dglgo/utils/factory.py
dglgo/utils/optimizer_config.py
dglgo/utils/yaml_dump.py
recipes/__init__.py
recipes/graphpred_hiv_gin.yaml
recipes/graphpred_hiv_pna.yaml
recipes/graphpred_pcba_gin.yaml
recipes/linkpred_citation2_sage.yaml
recipes/linkpred_collab_sage.yaml
dglgo-0.0.2.dist-info/METADATA
dglgo-0.0.2.dist-info/WHEEL
dglgo-0.0.2.dist-info/entry_points.txt
dglgo-0.0.2.dist-info/top_level.txt
dglgo-0.0.2.dist-info/RECORD
