Metadata-Version: 2.1
Name: dglgo
Version: 0.0.2
Summary: DGL
Home-page: https://github.com/dmlc/dgl
Author: DGL Team
Author-email: wmjlyjemaine@gmail.com
License: APACHE
Requires-Dist: typer (>=0.4.0)
Requires-Dist: isort (>=5.10.1)
Requires-Dist: autopep8 (>=1.6.0)
Requires-Dist: numpydoc (>=1.1.0)
Requires-Dist: pydantic (>=1.9.0)
Requires-Dist: ruamel.yaml (>=0.17.20)
Requires-Dist: PyYAML (>=5.1)
Requires-Dist: ogb (>=1.3.3)
Requires-Dist: rdkit-pypi
Requires-Dist: scikit-learn (>=0.20.0)
